findme/__init__.py
findme/__main__.py
findme/_cli.py
findme/tests/__init__.py
findme/tests/test_findme.py
findme-0.2.2.dist-info/COPYING
findme-0.2.2.dist-info/METADATA
findme-0.2.2.dist-info/WHEEL
findme-0.2.2.dist-info/entry_points.txt
findme-0.2.2.dist-info/top_level.txt
findme-0.2.2.dist-info/RECORD
