Metadata-Version: 2.1
Name: findme
Version: 0.2.2
Summary: A simple CLI for hypothesis.find
Home-page: https://github.com/Julian/findme
Author: Julian Berman
Author-email: Julian+findme@GrayVines.com
License: UNKNOWN
Project-URL: Source, https://github.com/Julian/findme
Project-URL: Issues, https://github.com/Julian/findme/issues/
Platform: UNKNOWN
Classifier: Development Status :: 3 - Alpha
Classifier: Operating System :: OS Independent
Classifier: Programming Language :: Python
Classifier: License :: OSI Approved :: MIT License
Classifier: Programming Language :: Python :: 2.7
Classifier: Programming Language :: Python :: 3.6
Classifier: Programming Language :: Python :: 3.7
Classifier: Programming Language :: Python :: 3.8
Classifier: Programming Language :: Python :: 2
Classifier: Programming Language :: Python :: 3
Classifier: Programming Language :: Python :: Implementation :: CPython
Classifier: Programming Language :: Python :: Implementation :: PyPy
Requires-Dist: click
Requires-Dist: hypothesis
Requires-Dist: importlib-metadata ; python_version < "3.8"
